{
  "taskDefinitionArn": "arn:aws:ecs:ap-northeast-2:555680551527:task-definition/ecs-oversweet-task:1",
  "containerDefinitions": [
    {
      "name": "oversweet-prod-image",
      "image": "555680551527.dkr.ecr.ap-northeast-2.amazonaws.com/oversweet-prod-image:latest",
      "cpu": 0,
      "portMappings": [
        {
          "containerPort": 8080,
          "hostPort": 80,
          "protocol": "tcp"
        }
      ],
      "essential": true,
      "entryPoint": [],
      "command": [],
      "environment": [],
      "mountPoints": [],
      "volumesFrom": []
    }
  ],
  "family": "ecs-oversweet-task",
  "taskRoleArn": "arn:aws:iam::555680551527:role/ecs-jejune-iam",
  "revision": 1,
  "volumes": [],
  "status": "ACTIVE",
  "requiresAttributes": [
    {
      "name": "com.amazonaws.ecs.capability.ecr-auth"
    },
    {
      "name": "com.amazonaws.ecs.capability.task-iam-role"
    }
  ],
  "placementConstraints": [],
  "compatibilities": [
    "EXTERNAL",
    "EC2"
  ],
  "requiresCompatibilities": [
    "EC2"
  ],
  "cpu": "512",
  "memory": "512",
  "registeredAt": "2023-06-06T12:02:56.252Z",
  "registeredBy": "arn:aws:iam::555680551527:root",
  "tags": []
}